src/design/7seg.sv
module module7SEG(
    input logic rst_pi,
    input logic [3:0] cod_bin,
    output logic [1:0] anodo_po,
    output logic [6:0] catodo_po
);

    // boton encendido muestra unidades y apagado las decenas
    assign anodo_po = (~rst_pi) ? 2'b01:2'b10;

    //Codigo biario en Conmutadores
    assign b1 = (cod_bin[3] == 1'b1) ? 1'b1 : 1'b0;
    assign b2 = (cod_bin[2] == 1'b1) ? 1'b1 : 1'b0;
    assign b3 = (cod_bin[1] == 1'b1) ? 1'b1 : 1'b0;
    assign b4 = (cod_bin[0] == 1'b1) ? 1'b1 : 1'b0;

    //7seg unidades
    assign seg_a = ((!b2) && (!b4)) || (b1 && (!b3)) || ((!b1) && b3) || (b2 && b4);
    assign seg_b = (!b3 && (!b4)) || (b1 && (!b3)) || (b1 && (!b4)) || (!b2) || ((!b1) && b3 && b4);
    assign seg_c = (b1 && (!b2)) || (b2 && b3) || ((!b1) && (!b3)) || (b4);
    assign seg_d = (b1 && (!b3)) || ((!b2) && (!b4)) || (b1 && b2 && b4) || ((!b1) && (!b2) && b3) || (b2 && (!b3) && b4) || ((!b1) && b3 && (!b4));
    assign seg_e = (b1 && (!b3) && (!b4)) || ((!b1) && b3 && (!b4)) || ((!b2) && (!b4));
    assign seg_f = ((!b1) && (!b3) && (!b4)) || ((!b1) && b2 && (!b3)) || (b1 && (!b2) && (!b3)) || (b1 && b3 && (!b4)) || (b1 && b2 && b3) || (b2 && b3 && (!b4));
    assign seg_g = (b2 && (!b3)) || (b1 && b2) || (b1 && (!b3)) || ((!b1) && b3 && (!b4)) || ((!b1) && (!b2) && b3);

    //7SEG DECENAS
    assign sd_X = (~b1) || ((~b2) && (~b3));
    assign sd_Y = 1'b1;
    assign sd_Z = 1'b0;

    //Salida
    assign catodo_po[6] = (anodo_po == 2'b10) ? sd_X : (anodo_po == 2'b01) ? seg_a : sd_Z;
    assign catodo_po[5] = (anodo_po == 2'b10) ? sd_Y : (anodo_po == 2'b01) ? seg_b : sd_Z;
    assign catodo_po[4] = (anodo_po == 2'b10) ? sd_Y : (anodo_po == 2'b01) ? seg_c : sd_Z;
    assign catodo_po[3] = (anodo_po == 2'b10) ? sd_X : (anodo_po == 2'b01) ? seg_d : sd_Z;
    assign catodo_po[2] = (anodo_po == 2'b10) ? sd_X : (anodo_po == 2'b01) ? seg_e : sd_Z;
    assign catodo_po[1] = (anodo_po == 2'b10) ? sd_X : (anodo_po == 2'b01) ? seg_f : sd_Z;
    assign catodo_po[0] = (anodo_po == 2'b10) ? sd_Z : (anodo_po == 2'b01) ? seg_g : sd_Z;

endmodule

src/design/bin_leds.sv
module moduleLED(
    input logic [3:0] cod_bin,
    input logic [3:0] codigo_bin_led_po  
);

    assign codigo_bin_led_po[0] = (cod_bin[0] == 1'b1) ? 1'b1:1'b0;
    assign codigo_bin_led_po[1] = (cod_bin[1] == 1'b1) ? 1'b1:1'b0;
    assign codigo_bin_led_po[2] = (cod_bin[2] == 1'b1) ? 1'b1:1'b0;
    assign codigo_bin_led_po[3] = (cod_bin[3] == 1'b1) ? 1'b1:1'b0;

endmodule

src/design/code_gray.sv
module moduleGray (
    input logic [3:0] codigo_gray_pi,
    output logic [3:0] cod_bin
);
    
    assign cod_bin[3] = codigo_gray_pi[3];
    assign cod_bin[2] = cod_bin[3] ^ codigo_gray_pi[2];
    assign cod_bin[1] = cod_bin[2] ^ codigo_gray_pi[1];
    assign cod_bin[0] = cod_bin[1] ^ codigo_gray_pi[0];

endmodule

src/sim/main_tb.sv
`timescale 1ns/1ps

module moduleMainTB;
    logic [3:0] gray;
    logic [3:0] bin;
    logic [3:0] led;
    logic [6:0] seg7;
    logic [1:0] disp;
    logic [0:0] button;



    moduleGray Conv(
        .codigo_gray_pi(gray),
        .cod_bin(bin)
    );

    moduleLED Verif(
    .cod_bin(bin),
    .codigo_bin_led_po(led)  
    );

    module7SEG Decod(
    .rst_pi(button),
    .cod_bin(bin),
    .anodo_po(disp),
    .catodo_po(seg7)
    );
    
    initial begin
        $monitor("Dec(%d), Bin(%b), Seg7(%b), displays(%b)", bin, bin, seg7, disp);
        gray = 4'b0000; #1; //valor inicial
        button = 0; #1;
        button = 1; #1;
        gray = 4'b0000; #1;
        
        button = 0; #2;
        gray = 4'b0001; #2;
        gray = 4'b0011; #3;
        gray = 4'b0010; #4;
        gray = 4'b0110; #5;
        gray = 4'b0111; #6;
        gray = 4'b0101; #7;
        gray = 4'b0100; #8;
        gray = 4'b1100; #9;
        gray = 4'b1101; #10;
        gray = 4'b1111; #11;
        gray = 4'b1110; #12;
        gray = 4'b1010; #13;
        gray = 4'b1011; #14;
        gray = 4'b1001; #15;
        gray = 4'b1000; #16;
        
        button = 1; #17; //simula que se presiono el boton
        gray = 4'b1101; #18;
        gray = 4'b1111; #19;
        gray = 4'b1110; #20;
        gray = 4'b1010; #21;
        gray = 4'b1011; #22;
        gray = 4'b1001; #23;
        gray = 4'b1000; #24;
    end

    initial begin
        $dumpfile("moduleMainTB.vcd");
        $dumpvars(0, moduleMainTB);
    end

endmodule

src/build/moduleMainTB.vcd
$date
	Mon Aug 26 19:48:46 2024
$end
$version
	Icarus Verilog
$end
$timescale
	1ps
$end
$scope module moduleMainTB $end
$var wire 7 ! seg7 [6:0] $end
$var wire 2 " disp [1:0] $end
$var wire 4 # bin [3:0] $end
$var reg 1 $ button $end
$var reg 4 % gray [3:0] $end
$var reg 4 & led [3:0] $end
$scope module Conv $end
$var wire 4 ' codigo_gray_pi [3:0] $end
$var wire 4 ( cod_bin [3:0] $end
$upscope $end
$scope module Decod $end
$var wire 4 ) cod_bin [3:0] $end
$var wire 1 $ rst_pi $end
$var wire 1 * sd_X $end
$var wire 1 + sd_Y $end
$var wire 1 , sd_Z $end
$var wire 1 - seg_a $end
$var wire 1 . seg_b $end
$var wire 1 / seg_c $end
$var wire 1 0 seg_d $end
$var wire 1 1 seg_e $end
$var wire 1 2 seg_f $end
$var wire 1 3 seg_g $end
$var wire 7 4 catodo_po [6:0] $end
$var wire 1 5 b4 $end
$var wire 1 6 b3 $end
$var wire 1 7 b2 $end
$var wire 1 8 b1 $end
$var wire 2 9 anodo_po [1:0] $end
$upscope $end
$scope module Verif $end
$var wire 4 : cod_bin [3:0] $end
$var wire 4 ; codigo_bin_led_po [3:0] $end
$upscope $end
$upscope $end
$enddefinitions $end
$comment Show the parameter values. $end
$dumpall
$end
#0
$dumpvars
bx ;
b0 :
bx 9
08
07
06
05
bx0 4
03
12
11
10
1/
1.
1-
0,
1+
1*
b0 )
b0 (
b0 '
bx &
b0 %
x$
b0 #
bx "
bx0 !
$end
#1000
b1111110 !
b1111110 4
b1 "
b1 9
0$
#2000
b10 "
b10 9
1$
#4000
b1 "
b1 9
0$
#6000
00
02
0-
b110000 !
b110000 4
01
15
b1 #
b1 (
b1 )
b1 :
b1 %
b1 '
#8000
11
b1101101 !
b1101101 4
10
0/
1-
05
13
16
b10 #
b10 (
b10 )
b10 :
b11 %
b11 '
#11000
01
b1111001 !
b1111001 4
1/
15
b11 #
b11 (
b11 )
b11 :
b10 %
b10 '
#15000
12
00
0-
b110011 !
b110011 4
1.
05
13
06
17
b100 #
b100 (
b100 )
b100 :
b110 %
b110 '
#20000
0.
b1011011 !
b1011011 4
10
1-
15
b101 #
b101 (
b101 )
b101 :
b111 %
b111 '
#26000
11
b1011111 !
b1011111 4
0.
05
16
b110 #
b110 (
b110 )
b110 :
b101 %
b101 '
#33000
b1110000 !
b1110000 4
01
03
00
02
1.
15
b111 #
b111 (
b111 )
b111 :
b100 %
b100 '
#41000
11
10
05
b1111111 !
b1111111 4
13
12
06
1-
1*
07
18
b1000 #
b1000 (
b1000 )
b1000 :
b1100 %
b1100 '
#50000
b1111011 !
b1111011 4
01
15
b1001 #
b1001 (
b1001 )
b1001 :
b1101 %
b1101 '
#60000
10
b1111110 !
b1111110 4
12
11
1-
03
0*
05
16
b1010 #
b1010 (
b1010 )
b1010 :
b1111 %
b1111 '
#71000
00
0-
b110000 !
b110000 4
02
01
15
b1011 #
b1011 (
b1011 )
b1011 :
b1110 %
b1110 '
#83000
11
10
13
0/
b1101101 !
b1101101 4
05
1.
1-
06
17
b1100 #
b1100 (
b1100 )
b1100 :
b1010 %
b1010 '
#96000
01
b1111001 !
b1111001 4
1/
15
b1101 #
b1101 (
b1101 )
b1101 :
b1011 %
b1011 '
#110000
00
1.
b110011 !
b110011 4
0-
12
05
16
b1110 #
b1110 (
b1110 )
b1110 :
b1001 %
b1001 '
#125000
10
0.
b1011011 !
b1011011 4
1-
15
b1111 #
b1111 (
b1111 )
b1111 :
b1000 %
b1000 '
#141000
b110000 !
b110000 4
b10 "
b10 9
1$
#158000
b1111110 !
b1111110 4
1*
10
1.
06
01
1-
07
15
b1001 #
b1001 (
b1001 )
b1001 :
b1101 %
b1101 '
#176000
10
12
11
1-
03
b110000 !
b110000 4
0*
05
16
b1010 #
b1010 (
b1010 )
b1010 :
b1111 %
b1111 '
#195000
00
0-
02
01
15
b1011 #
b1011 (
b1011 )
b1011 :
b1110 %
b1110 '
#215000
11
10
13
0/
05
1.
1-
06
17
b1100 #
b1100 (
b1100 )
b1100 :
b1010 %
b1010 '
#236000
01
1/
15
b1101 #
b1101 (
b1101 )
b1101 :
b1011 %
b1011 '
#258000
00
1.
0-
12
05
16
b1110 #
b1110 (
b1110 )
b1110 :
b1001 %
b1001 '
#281000
10
0.
1-
15
b1111 #
b1111 (
b1111 )
b1111 :
b1000 %
b1000 '
