src/design/code_gray.sv
module moduleGray (
    input logic [3:0] codigo_gray_pi,
    output logic [3:0] cod_bin
);
    
    assign cod_bin[3] = codigo_gray_pi[3];
    assign cod_bin[2] = cod_bin[3] ^ codigo_gray_pi[2];
    assign cod_bin[1] = cod_bin[2] ^ codigo_gray_pi[1];
    assign cod_bin[0] = cod_bin[1] ^ codigo_gray_pi[0];

endmodule

src/sim/code_gray_tb.sv
`timescale 1ns/1ps

module moduleGrayTB;
    logic [3:0] gray;
    logic [3:0] bin;

    moduleGray Conv(
        .codigo_gray_pi(gray),
        .cod_bin(bin)
    );

    initial begin
        $monitor("Codigo Binario = %b", bin);
        gray = 4'b0000; #1;
        gray = 4'b0001; #2;
        gray = 4'b0011; #3;
        gray = 4'b0010; #4;
        gray = 4'b0110; #5;
        gray = 4'b0111; #6;
        gray = 4'b0101; #7;
        gray = 4'b0100; #8;
        gray = 4'b1100; #9;
        gray = 4'b1101; #10;
        gray = 4'b1111; #11;
        gray = 4'b1110; #12;
        gray = 4'b1010; #13;
        gray = 4'b1011; #14;
        gray = 4'b1001; #15;
        gray = 4'b1000;
    end

    initial begin
        $dumpfile("moduleGrayTB.vcd");
        $dumpvars(0, moduleGrayTB);
    end

endmodule

src/build/moduleGrayTB.vcd
$date
	Thu Aug 22 15:36:18 2024
$end
$version
	Icarus Verilog
$end
$timescale
	1ps
$end
$scope module moduleGrayTB $end
$var wire 4 ! bin [3:0] $end
$var reg 4 " gray [3:0] $end
$scope module Conv $end
$var wire 4 # codigo_gray_pi [3:0] $end
$var wire 4 $ cod_bin [3:0] $end
$upscope $end
$upscope $end
$enddefinitions $end
$comment Show the parameter values. $end
$dumpall
$end
#0
$dumpvars
b0 $
b0 #
b0 "
b0 !
$end
#1000
b1 !
b1 $
b1 "
b1 #
#3000
b10 !
b10 $
b11 "
b11 #
#6000
b11 !
b11 $
b10 "
b10 #
#10000
b100 !
b100 $
b110 "
b110 #
#15000
b101 !
b101 $
b111 "
b111 #
#21000
b110 !
b110 $
b101 "
b101 #
#28000
b111 !
b111 $
b100 "
b100 #
#36000
b1000 !
b1000 $
b1100 "
b1100 #
#45000
b1001 !
b1001 $
b1101 "
b1101 #
#55000
b1010 !
b1010 $
b1111 "
b1111 #
#66000
b1011 !
b1011 $
b1110 "
b1110 #
#78000
b1100 !
b1100 $
b1010 "
b1010 #
#91000
b1101 !
b1101 $
b1011 "
b1011 #
#105000
b1110 !
b1110 $
b1001 "
b1001 #
#120000
b1111 !
b1111 $
b1000 "
b1000 #
